{
  "version": 1,
  "generatedAt": "2026-02-15T14:33:45.417Z",
  "modules": [
    {
      "name": "code-development",
      "entry": "code-development/index.html",
      "browserPath": "code-development/browser",
      "files": {
        "js": [
          "chunk-QMK3QNP7.js",
          "chunk-WMA6ZS3S.js",
          "main-K3RXR6SI.js",
          "polyfills-5CFQRCPP.js"
        ],
        "css": [
          "styles-Z5UYKNDX.css"
        ]
      }
    },
    {
      "name": "data-integration",
      "entry": "data-integration/index.html",
      "browserPath": "data-integration/browser",
      "files": {
        "js": [
          "chunk-LEHMRPA4.js",
          "chunk-LV2NJSWB.js",
          "main-G77RTI4T.js",
          "polyfills-5CFQRCPP.js"
        ],
        "css": [
          "styles-Z5UYKNDX.css"
        ]
      }
    }
  ]
}